bumbo/__init__.py
bumbo/api.py
bumbo/middleware.py
bumbo/response.py
Ma_Jbumbo-0.0.2.dist-info/METADATA
Ma_Jbumbo-0.0.2.dist-info/WHEEL
Ma_Jbumbo-0.0.2.dist-info/top_level.txt
Ma_Jbumbo-0.0.2.dist-info/RECORD
