Metadata-Version: 2.1
Name: Ma-Jbumbo
Version: 0.0.2
Summary: My JBumbo Python Web Framework built for learning purposes.
Author: Raah mann
Author-email: sjavaidx@gmail.com
License: MIT
Classifier: Programming Language :: Python :: 3.6
Requires-Python: >=3.6.0
Requires-Dist: Jinja2 (==2.10.3)
Requires-Dist: parse (==1.12.1)
Requires-Dist: requests (==2.22.0)
Requires-Dist: requests-wsgi-adapter (==0.4.1)
Requires-Dist: WebOb (==1.8.5)
Requires-Dist: whitenoise (==4.1.4)
